abacatepay/__init__.py
abacatepay/base/___init___.py
abacatepay/base/client.py
abacatepay/billings/__init__.py
abacatepay/billings/client.py
abacatepay/billings/models.py
abacatepay/constants.py
abacatepay/coupons/__init__.py
abacatepay/coupons/client.py
abacatepay/coupons/models.py
abacatepay/customers/__init__.py
abacatepay/customers/client.py
abacatepay/customers/models.py
abacatepay/pixQrCode/__init__.py
abacatepay/pixQrCode/client.py
abacatepay/pixQrCode/models.py
abacatepay/products/__init__.py
abacatepay/products/models.py
abacatepay/utils/exceptions.py
abacatepay/utils/helpers.py
abacatepay-1.0.9.dist-info/METADATA
abacatepay-1.0.9.dist-info/WHEEL
abacatepay-1.0.9.dist-info/RECORD
