Metadata-Version: 2.3
Name: abacatepay
Version: 1.0.9
Summary: Python SDK to interact with AbacatePay's API
Author: Joaquim Cassano
Author-email: joaquim@cassano.com.br
Requires-Python: >=3.10,<4.0
Classifier: Programming Language :: Python :: 3
Classifier: Programming Language :: Python :: 3.10
Classifier: Programming Language :: Python :: 3.11
Classifier: Programming Language :: Python :: 3.12
Classifier: Programming Language :: Python :: 3.13
Requires-Dist: httpx (>=0.28.1,<0.29.0)
Requires-Dist: pydantic (>=2.10.3,<3.0.0)
Requires-Dist: requests (>=2.32.3,<3.0.0)
